setup.py
pyfribidi/__init__.py
pyfribidi/fribidi.c
python_fribidi.egg-info/PKG-INFO
python_fribidi.egg-info/SOURCES.txt
python_fribidi.egg-info/dependency_links.txt
python_fribidi.egg-info/top_level.txt