Metadata-Version: 1.0
Name: python-fribidi
Version: 0.1.0
Summary: Python(Cython) Binding for Fribidi The Free Implementation of the Unicode Bidirectional Algorithm.
Home-page: https://github.com/RevengeComing/python-fribidi
Author: Sepehr Hamzehlouy
Author-email: s.hamzelooy@gmail.com
License: MIT
Platform: UNKNOWN
